package/__init__.py
package/modul1.py
package/modul2.py
tom_rtc-0.1.0.dist-info/METADATA
tom_rtc-0.1.0.dist-info/WHEEL
tom_rtc-0.1.0.dist-info/top_level.txt
tom_rtc-0.1.0.dist-info/RECORD
