Metadata-Version: 2.1
Name: tom-rtc
Version: 0.1.0
Summary: Tom sein Modul
Home-page: UNKNOWN
Author: Tom RtC
Author-email: UNKNOWN
License: UNKNOWN
Keywords: python,code
Platform: UNKNOWN
Classifier: Development Status :: 1 - Planning
Classifier: Intended Audience :: Developers
Classifier: Programming Language :: Python :: 3
Classifier: Operating System :: Microsoft :: Windows
Classifier: Operating System :: POSIX :: Linux
Requires-Dist: numpy
